LICENSE.txt
README.md
setup.py
forecasting_models/__init__.py
forecasting_models/gradient_boosting_model.py
forecasting_models/mlp_regressor.py
forecasting_models/prophet_model.py
forecasting_models/random_forest_model.py
forecasting_models/xgboost_model.py
forecasting_models.egg-info/PKG-INFO
forecasting_models.egg-info/SOURCES.txt
forecasting_models.egg-info/dependency_links.txt
forecasting_models.egg-info/requires.txt
forecasting_models.egg-info/top_level.txt