Metadata-Version: 2.1
Name: forecasting_models
Version: 0.1
Summary: Advanced Time Series Forecasting Suite: Leveraging Diverse Models for Predictive Analytics
Home-page: https://github.com/knowusuboaky/forecasting_models
Author: Kwadwo Daddy Nyame Owusu - Boakye
Author-email: kwadwo.owusuboakye@outlook.com
Keywords: forecasting time-series prophet xgboost random-forest mlp gradient-boosting
Classifier: Development Status :: 3 - Alpha
Classifier: Intended Audience :: Developers
Classifier: Topic :: Software Development :: Build Tools
Classifier: License :: OSI Approved :: MIT License
Classifier: Programming Language :: Python :: 3
Classifier: Programming Language :: Python :: 3.6
Classifier: Programming Language :: Python :: 3.7
Classifier: Programming Language :: Python :: 3.8
Classifier: Programming Language :: Python :: 3.9
Classifier: Programming Language :: Python :: 3.10
Classifier: Programming Language :: Python :: 3.11
Classifier: Programming Language :: Python :: 3.12
Requires-Python: >=3.6
License-File: LICENSE.txt
Requires-Dist: pandas
Requires-Dist: numpy
Requires-Dist: scikit-learn
Requires-Dist: statsmodels
Requires-Dist: prophet
Requires-Dist: xgboost
